{
  "aggregations" : {
    "by_build" : {
      "buckets" : [ {
        "key" : "1361",
        "status" : {
          "buckets" : [ {
            "key" : "failure"
          }, {
            "key" : "started"
          } ]
        }
      }, {
        "key" : "1241",
        "status" : {
          "buckets" : [ {
            "key" : "failure"
          } ]
        }
      }, {
        "key" : "1244",
        "status" : {
          "buckets" : [ {
            "key" : "failure"
          } ]
        }
      }, {
        "key" : "1247",
        "status" : {
          "buckets" : [ {
            "key" : "failure"
          } ]
        }
      }, {
        "key" : "1248",
        "status" : {
          "buckets" : [ {
            "key" : "failure"
          } ]
        }
      }, {
        "key" : "1249",
        "status" : {
          "buckets" : [ {
            "key" : "failure"
          } ]
        }
      }, {
        "key" : "1250",
        "status" : {
          "buckets" : [ {
            "key" : "failure"
          } ]
        }
      }, {
        "key" : "1251",
        "status" : {
          "buckets" : [ {
            "key" : "failure"
          } ]
        }
      }, {
        "key" : "1252",
        "status" : {
          "buckets" : [ {
            "key" : "failure"
          } ]
        }
      }, {
        "key" : "1253",
        "status" : {
          "buckets" : [ {
            "key" : "failure"
          } ]
        }
      }, {
        "key" : "1254",
        "status" : {
          "buckets" : [ {
            "key" : "failure"
          } ]
        }
      }, {
        "key" : "1255",
        "status" : {
          "buckets" : [ {
            "key" : "failure"
          } ]
        }
      }, {
        "key" : "1256",
        "status" : {
          "buckets" : [ {
            "key" : "failure"
          } ]
        }
      }, {
        "key" : "1257",
        "status" : {
          "buckets" : [ {
            "key" : "failure"
          } ]
        }
      }, {
        "key" : "1258",
        "status" : {
          "buckets" : [ {
            "key" : "failure"
          } ]
        }
      }, {
        "key" : "1259",
        "status" : {
          "buckets" : [ {
            "key" : "success"
          } ]
        }
      }, {
        "key" : "1261",
        "status" : {
          "buckets" : [ {
            "key" : "failure"
          } ]
        }
      }, {
        "key" : "1264",
        "status" : {
          "buckets" : [ {
            "key" : "success"
          } ]
        }
      }, {
        "key" : "1265",
        "status" : {
          "buckets" : [ {
            "key" : "failure"
          } ]
        }
      }, {
        "key" : "1267",
        "status" : {
          "buckets" : [ {
            "key" : "failure"
          } ]
        }
      }, {
        "key" : "1271",
        "status" : {
          "buckets" : [ {
            "key" : "failure"
          } ]
        }
      }, {
        "key" : "1274",
        "status" : {
          "buckets" : [ {
            "key" : "failure"
          } ]
        }
      }, {
        "key" : "1275",
        "status" : {
          "buckets" : [ {
            "key" : "failure"
          } ]
        }
      }, {
        "key" : "1278",
        "status" : {
          "buckets" : [ {
            "key" : "failure"
          } ]
        }
      }, {
        "key" : "1279",
        "status" : {
          "buckets" : [ {
            "key" : "failure"
          } ]
        }
      }, {
        "key" : "1281",
        "status" : {
          "buckets" : [ {
            "key" : "failure"
          } ]
        }
      }, {
        "key" : "1285",
        "status" : {
          "buckets" : [ {
            "key" : "aborted"
          } ]
        }
      }, {
        "key" : "1286",
        "status" : {
          "buckets" : [ {
            "key" : "success"
          } ]
        }
      }, {
        "key" : "1293",
        "status" : {
          "buckets" : [ {
            "key" : "failure"
          } ]
        }
      }, {
        "key" : "1298",
        "status" : {
          "buckets" : [ {
            "key" : "success"
          } ]
        }
      }, {
        "key" : "1356",
        "status" : {
          "buckets" : [ {
            "key" : "failure"
          } ]
        }
      }, {
        "key" : "1357",
        "status" : {
          "buckets" : [ {
            "key" : "failure"
          } ]
        }
      }, {
        "key" : "1358",
        "status" : {
          "buckets" : [ {
            "key" : "failure"
          } ]
        }
      }, {
        "key" : "1359",
        "status" : {
          "buckets" : [ {
            "key" : "failure"
          } ]
        }
      }, {
        "key" : "1362",
        "status" : {
          "buckets" : [ {
            "key" : "failure"
          } ]
        }
      }, {
        "key" : "1363",
        "status" : {
          "buckets" : [ {
            "key" : "failure"
          } ]
        }
      }, {
        "key" : "1364",
        "status" : {
          "buckets" : [ {
            "key" : "failure"
          } ]
        }
      }, {
        "key" : "1365",
        "status" : {
          "buckets" : [ {
            "key" : "started"
          } ]
        }
      }, {
        "key" : "1366",
        "status" : {
          "buckets" : [ {
            "key" : "failure"
          } ]
        }
      }, {
        "key" : "1368",
        "status" : {
          "buckets" : [ {
            "key" : "failure"
          } ]
        }
      }, {
        "key" : "1369",
        "status" : {
          "buckets" : [ {
            "key" : "failure"
          } ]
        }
      }, {
        "key" : "1370",
        "status" : {
          "buckets" : [ {
            "key" : "failure"
          } ]
        }
      }, {
        "key" : "1371",
        "status" : {
          "buckets" : [ {
            "key" : "failure"
          } ]
        }
      }, {
        "key" : "1372",
        "status" : {
          "buckets" : [ {
            "key" : "failure"
          } ]
        }
      }, {
        "key" : "1373",
        "status" : {
          "buckets" : [ {
            "key" : "failure"
          } ]
        }
      }, {
        "key" : "1375",
        "status" : {
          "buckets" : [ {
            "key" : "failure"
          } ]
        }
      }, {
        "key" : "1376",
        "status" : {
          "buckets" : [ {
            "key" : "failure"
          } ]
        }
      }, {
        "key" : "1377",
        "status" : {
          "buckets" : [ {
            "key" : "failure"
          } ]
        }
      }, {
        "key" : "1378",
        "status" : {
          "buckets" : [ {
            "key" : "failure"
          } ]
        }
      }, {
        "key" : "1379",
        "status" : {
          "buckets" : [ {
            "key" : "failure"
          } ]
        }
      } ]
    }
  }
}
